kenworthy/__init__.py
kenworthy/exorings3.py
kenworthy/isocosa.py
kenworthy/kepler3.py
kenworthy/tag_plot.py
kenworthy-0.1.2.dist-info/LICENSE
kenworthy-0.1.2.dist-info/METADATA
kenworthy-0.1.2.dist-info/WHEEL
kenworthy-0.1.2.dist-info/top_level.txt
kenworthy-0.1.2.dist-info/RECORD
